setup.py
ljfuncs/__init__.py
ljfuncs.egg-info/PKG-INFO
ljfuncs.egg-info/SOURCES.txt
ljfuncs.egg-info/dependency_links.txt
ljfuncs.egg-info/top_level.txt