Metadata-Version: 1.0
Name: ljfuncs
Version: 1.0.0
Summary: Functions for analysing friends and interests lists on Livejournal.
Home-page: http://www.site.uottawa.ca/~mraap046
Author: Sebastian Raaphorst
Author-email: srcoding@gmail.com
License: Apache 2.0
Keywords: livejournal lj blogging blog
Platform: UNKNOWN
Classifier: License :: OSI Approved :: Apache Software License
Classifier: Programming Language :: Python
Classifier: Development Status :: 4 - Beta
Classifier: Intended Audience :: Developers
Classifier: Topic :: Communications
